{"name": "Stasiun_televisi", "id": 14673, "predecessors": [{"name": "Televisi", "id": 8538}, {"name": "Penyiaran", "id": 304596}], "successors": [{"name": "Stasiun_televisi_Jepang", "id": 17259}, {"name": "Stasiun_televisi_Spanyol", "id": 38180}, {"name": "Stasiun_televisi_Indonesia", "id": 76903}, {"name": "Stasiun_televisi_Britania_Raya", "id": 97059}, {"name": "Stasiun_televisi_Amerika_Serikat", "id": 106707}, {"name": "Stasiun_televisi_Filipina", "id": 157561}, {"name": "Stasiun_televisi_Malaysia", "id": 180288}, {"name": "Stasiun_televisi_India", "id": 246142}, {"name": "Stasiun_televisi_Korea_Selatan", "id": 308883}, {"name": "Stasiun_televisi_Singapura", "id": 763966}, {"name": "Jaringan_televisi_Prancis", "id": 290485}, {"name": "Daftar_stasiun_televisi_di_Indonesia", "id": 3613756}]}