{"name": "Film_Hong_Kong", "id": 15455, "predecessors": [{"name": "Film_Tiongkok", "id": 1474851}, {"name": "Tiongkok", "id": 1468418}], "successors": [{"name": "Pemeran_Hong_Kong", "id": 133298}, {"name": "Sutradara_Hong_Kong", "id": 285860}, {"name": "Film_berbahasa_Kanton", "id": 323056}, {"name": "Film_Hong_Kong_tahun_2009", "id": 385798}, {"name": "Film_Hong_Kong_tahun_2006", "id": 385917}, {"name": "Film_Hong_Kong_tahun_2010", "id": 489757}, {"name": "Film_Hong_Kong_tahun_2011", "id": 785644}, {"name": "Film_Hong_Kong_tahun_2016", "id": 2119268}]}