{"name": "Jawa_Barat", "id": 16066, "predecessors": [{"name": "Provinsi_di_Indonesia", "id": 604013}, {"name": "Pembagian_administratif_Indonesia", "id": 84525}], "successors": [{"name": "Tokoh_Jawa_Barat", "id": 109550}, {"name": "Stasiun_radio_di_Jawa_Barat", "id": 436072}, {"name": "Sejarah_Jawa_Barat", "id": 458745}, {"name": "Stasiun_televisi_di_Jawa_Barat", "id": 473585}, {"name": "Air_terjun_di_Jawa_Barat", "id": 1071533}, {"name": "Daftar_kecamatan_dan_kelurahan_di_Jawa_Barat", "id": 3201373}, {"name": "Stasiun_kereta_api_di_Jawa_Barat", "id": 340341}, {"name": "Terminal_bus_di_Jawa_Barat", "id": 2161738}, {"name": "Perguruan_tinggi_di_Jawa_Barat", "id": 331327}, {"name": "Tempat_wisata_di_Jawa_Barat", "id": 91234}, {"name": "Klub_sepak_bola_di_Jawa_Barat", "id": 1435466}, {"name": "Rumah_sakit_di_Jawa_Barat", "id": 349903}, {"name": "Rumah_sakit_di_Kota_Depok", "id": 3700728}, {"name": "Dewan_Perwakilan_Rakyat_Daerah_Kabupaten/Kota_di_Jawa_Barat", "id": 3203439}, {"name": "Pemilihan_umum_bupati_di_Jawa_Barat", "id": 1118650}, {"name": "Pemilihan_umum_wali_kota_di_Jawa_Barat", "id": 3346556}, {"name": "Jalan_tol_di_Jawa_Barat", "id": 2135275}]}