{"name": "Meksiko", "id": 19607, "predecessors": [{"name": "Negara", "id": 14449}, {"name": "Geografi", "id": 8558}], "successors": [{"name": "Tokoh_Meksiko", "id": 56104}, {"name": "Sejarah_Meksiko", "id": 274145}, {"name": "Grand_Prix_Meksiko", "id": 442982}, {"name": "Kota_di_Meksiko", "id": 48082}, {"name": "Negara_bagian_di_Meksiko", "id": 50258}, {"name": "Pemain_sepak_bola_Meksiko", "id": 67937}, {"name": "Stadion_sepak_bola_di_Meksiko", "id": 3023914}, {"name": "Film_Meksiko", "id": 463741}, {"name": "Pemeran_film_laki-laki_Meksiko", "id": 3257447}, {"name": "Hidangan_Meksiko", "id": 288293}, {"name": "Klub_sepak_bola_Meksiko", "id": 62209}, {"name": "Bandar_udara_di_Meksiko", "id": 56066}, {"name": "Basilika_di_Meksiko", "id": 4247045}, {"name": "Katedral_Katolik_di_Meksiko", "id": 4247059}]}