{"name": "Desa_di_Kepulauan_Bangka_Belitung", "id": 2143965, "predecessors": [{"name": "Pembagian_administratif", "id": 70757}, {"name": "Pembagian_administratif_Indonesia", "id": 84525}], "successors": [{"name": "Desa_di_Kabupaten_Belitung", "id": 377353}, {"name": "Desa_di_Kabupaten_Belitung_Timur", "id": 546066}, {"name": "Desa_di_Kabupaten_Bangka_Barat", "id": 612675}, {"name": "Desa_di_Kabupaten_Bangka_Tengah", "id": 688726}, {"name": "Desa_di_Kabupaten_Bangka", "id": 712608}, {"name": "Desa_di_Kabupaten_Bangka_Selatan", "id": 2144096}]}