{"name": "Perusahaan_pengembang_permainan_video", "id": 3154548, "predecessors": [{"name": "Perusahaan_permainan_video", "id": 186721}, {"name": "Pengembangan_perangkat_lunak", "id": 132721}], "successors": [{"name": "Permainan_Sony_Interactive_Entertainment", "id": 2073044}, {"name": "Permainan_PlayStation", "id": 107918}, {"name": "Permainan_PlayStation_2", "id": 187184}, {"name": "Permainan_PlayStation_3", "id": 188247}, {"name": "Permainan_PlayStation_Portable", "id": 952735}, {"name": "Permainan_PlayStation_4", "id": 2073101}, {"name": "Permainan_PlayStation_5", "id": 3210937}]}