{"name": "Hukum_di_Indonesia", "id": 48202, "predecessors": [{"name": "Adat", "id": 44816}, {"name": "Hukum", "id": 8535}, {"name": "Pancasila", "id": 14448}, {"name": "Parlemen", "id": 96200}, {"name": "Pemerintahan_Indonesia", "id": 146279}, {"name": "Asia", "id": 10800}], "successors": [{"name": "Perpajakan_di_Indonesia", "id": 137410}, {"name": "Tokoh_hukum_Indonesia", "id": 195328}, {"name": "Traktat_yang_melibatkan_Indonesia", "id": 286084}, {"name": "Kejaksaan_Indonesia", "id": 593698}, {"name": "Penjara_di_Indonesia", "id": 1563811}, {"name": "Pendidikan_hukum_di_Indonesia", "id": 2077948}, {"name": "Lembaga_peradilan_Indonesia", "id": 66981}, {"name": "Komisi_Pemberantasan_Korupsi", "id": 617719}, {"name": "Undang-Undang_Indonesia", "id": 2965940}]}