{"name": "Templat_pemeliharaan", "id": 51263, "predecessors": [{"name": "Pemeliharaan_Wikipedia", "id": 51259}, {"name": "Templat_Wikipedia", "id": 127053}], "successors": [{"name": "Templat_rintisan", "id": 51138}, {"name": "Templat_pemungutan_suara", "id": 67741}, {"name": "Templat_berisiko_tinggi", "id": 139242}, {"name": "Templat_info_artikel", "id": 240740}, {"name": "Templat_disambiguasi", "id": 253358}, {"name": "Templat_bantuan", "id": 276153}, {"name": "Templat_pengalihan", "id": 294287}, {"name": "Templat_penghapusan", "id": 2346972}, {"name": "Kotak_pesan_pembicaraan", "id": 2966876}, {"name": "Templat_catatan_topi_untuk_nama", "id": 2068791}, {"name": "Templat_klasifikasi", "id": 781925}, {"name": "Templat_pemeliharaan_rujukan_dan_pemastian", "id": 2598759}]}