{"name": "Kecamatan_di_Sulawesi_Selatan", "id": 53869, "predecessors": [{"name": "Pembagian_administratif_Indonesia", "id": 84525}], "successors": [{"name": "Kecamatan_di_Kabupaten_Bone", "id": 71438}, {"name": "Kecamatan_di_Kabupaten_Gowa", "id": 89907}, {"name": "Kecamatan_di_Kabupaten_Luwu", "id": 89979}, {"name": "Kecamatan_di_Kabupaten_Luwu_Utara", "id": 90019}, {"name": "Kecamatan_di_Kabupaten_Tana_Toraja", "id": 90204}, {"name": "Kecamatan_di_Kota_Makassar", "id": 90260}, {"name": "Kecamatan_di_Kabupaten_Toraja_Utara", "id": 312216}]}