{"name": "Media", "id": 56383, "predecessors": [{"name": "Komunikasi", "id": 8533}], "successors": [{"name": "Komik", "id": 14459}, {"name": "Penerbit", "id": 17049}, {"name": "Ensiklopedia", "id": 41406}, {"name": "Genre_sastra", "id": 21997}, {"name": "Genre_musik", "id": 127728}, {"name": "Genre_permainan_video", "id": 186228}, {"name": "Genre_televisi", "id": 285176}, {"name": "Genre_teater", "id": 815179}, {"name": "Genre_film", "id": 963642}, {"name": "Musim_televisi_Indonesia_tahun_2018", "id": 2717275}, {"name": "Musim_televisi_Indonesia_tahun_2017", "id": 2717279}, {"name": "Musim_televisi_Indonesia_tahun_2022", "id": 3406551}, {"name": "Perusahaan_media_Indonesia", "id": 304814}]}