{"name": "Sejarah_Eropa", "id": 56700, "predecessors": [{"name": "Eropa", "id": 15962}, {"name": "Sejarah", "id": 8501}], "successors": [{"name": "Sejarah_Jerman", "id": 19647}, {"name": "Sejarah_Norwegia", "id": 26654}, {"name": "Sejarah_Rumania", "id": 39369}, {"name": "Abad_Pertengahan", "id": 45543}, {"name": "Sejarah_Italia", "id": 51864}, {"name": "Sejarah_Inggris", "id": 116968}, {"name": "Sejarah_Bulgaria", "id": 215823}, {"name": "Al-Andalus", "id": 222835}, {"name": "Bekas_negara_di_Eropa", "id": 234754}, {"name": "Sejarah_Serbia", "id": 285194}, {"name": "Sejarah_Irlandia", "id": 337932}, {"name": "Sejarah_Georgia", "id": 428843}, {"name": "Romantisisme", "id": 462094}, {"name": "Sejarah_Skotlandia", "id": 462200}, {"name": "Romawi", "id": 610075}, {"name": "Mitologi_Nordik", "id": 161478}, {"name": "Viking", "id": 1899713}, {"name": "Penguasa_monarki_Bohemia", "id": 804077}, {"name": "Pertempuran_dan_operasi_militer_dalam_Perang_Dunia_II_di_Eropa", "id": 438715}, {"name": "Wangsa_Kapetia", "id": 781799}, {"name": "Holokaus", "id": 47313}, {"name": "Abad_Pencerahan", "id": 2950099}, {"name": "Perang_Dunia_II", "id": 10247}, {"name": "Sejarah_kepausan", "id": 2136135}, {"name": "Prancis_dalam_tahun_1914", "id": 460697}, {"name": "Britania_Raya_dalam_tahun_1914", "id": 462031}, {"name": "Jerman_dalam_tahun_1914", "id": 462035}, {"name": "Jerman_dalam_tahun_1916", "id": 462063}, {"name": "Britania_Raya_dalam_tahun_1916", "id": 462225}]}