{"name": "Filsafat", "id": 8559, "predecessors": [{"name": "Budaya", "id": 8546}, {"name": "Ilmu_sosial", "id": 51276}, {"name": "Isi", "id": 358984}], "successors": [{"name": "Hukum", "id": 8535}, {"name": "Filsuf", "id": 17451}, {"name": "Teologi", "id": 41318}, {"name": "Etika", "id": 70759}, {"name": "Filsafat_sosial", "id": 83530}, {"name": "Metafisika", "id": 123924}, {"name": "Ateisme", "id": 134192}, {"name": "Istilah_filsafat", "id": 359376}, {"name": "Konsep_filosofis", "id": 457983}, {"name": "Estetika", "id": 462287}, {"name": "Buku_filsafat", "id": 462291}, {"name": "Filsafat_Barat", "id": 462996}, {"name": "Moral", "id": 641063}, {"name": "Filsafat_agama", "id": 739933}, {"name": "Pascamodernisme", "id": 1753590}, {"name": "Dialog_Plato", "id": 1808459}, {"name": "Kepercayaan", "id": 10899}, {"name": "Angka", "id": 16630}, {"name": "Emosi", "id": 43114}, {"name": "Simbol", "id": 65250}, {"name": "Informasi", "id": 77026}, {"name": "Pikiran", "id": 285214}, {"name": "Metafora", "id": 3187837}, {"name": "Permainan_kata", "id": 78252}, {"name": "Kelas_kata", "id": 158411}, {"name": "Neologisme", "id": 825768}, {"name": "Logika", "id": 30288}, {"name": "Teori_etika", "id": 600738}, {"name": "Filsafat_budi", "id": 1492499}, {"name": "Kepribadian", "id": 1960475}, {"name": "Transhumanisme", "id": 3910311}, {"name": "Neoplatonis", "id": 2903693}, {"name": "Persinyalan_kereta_api", "id": 2780731}, {"name": "Pernikahan", "id": 126084}, {"name": "Baptis", "id": 3887037}]}